.coveragerc
LICENSE.txt
MANIFEST.in
Makefile
NOTICE.txt
README.rst
requirements.txt
setup.py
tox.ini
tests/__init__.py
tests/test_mixins.py
unittest_mixins/__init__.py
unittest_mixins/mixins.py
unittest_mixins.egg-info/PKG-INFO
unittest_mixins.egg-info/SOURCES.txt
unittest_mixins.egg-info/dependency_links.txt
unittest_mixins.egg-info/requires.txt
unittest_mixins.egg-info/top_level.txt